mylib_051/__init__.py
mylib_051-0.1.dist-info/LICENSE.txt
mylib_051-0.1.dist-info/METADATA
mylib_051-0.1.dist-info/WHEEL
mylib_051-0.1.dist-info/top_level.txt
mylib_051-0.1.dist-info/RECORD
